cs/__init__.py
cs/py.typed
cs/util.py
cs/algorithms/__init__.py
cs/algorithms/binary_search.py
cs/algorithms/optimal_bst.py
cs/algorithms/quick_select.py
cs/algorithms/rabbit.py
cs/algorithms/compression/__init__.py
cs/algorithms/compression/burrows_wheeler.py
cs/algorithms/compression/huffman.py
cs/algorithms/graph/__init__.py
cs/algorithms/graph/bellman_ford.py
cs/algorithms/graph/bfs.py
cs/algorithms/graph/connected.py
cs/algorithms/graph/dfs.py
cs/algorithms/graph/dijkstras.py
cs/algorithms/graph/edmonds_karp.py
cs/algorithms/graph/floyd_warshall.py
cs/algorithms/graph/ford_fulkerson.py
cs/algorithms/graph/hamiltonian_cycle.py
cs/algorithms/graph/johnsons.py
cs/algorithms/graph/kargers.py
cs/algorithms/graph/kruskals.py
cs/algorithms/graph/prims.py
cs/algorithms/graph/toposort.py
cs/algorithms/sort/__init__.py
cs/algorithms/sort/bubble_sort.py
cs/algorithms/sort/bucket_sort.py
cs/algorithms/sort/insertion_sort.py
cs/algorithms/sort/merge_sort.py
cs/algorithms/sort/quick_sort.py
cs/algorithms/sort/radix_sort.py
cs/algorithms/sort/selection_sort.py
cs/algorithms/string/__init__.py
cs/algorithms/string/knuth_morris_pratt.py
cs/algorithms/string/lcs.py
cs/algorithms/string/sais.py
cs/maths/__init__.py
cs/maths/basic_ops.py
cs/maths/bits.py
cs/maths/factorial.py
cs/maths/fibonacci.py
cs/maths/karatsuba.py
cs/maths/conversions/__init__.py
cs/maths/conversions/molecular_chemistry.py
cs/maths/conversions/morse_code.py
cs/maths/conversions/roman_to_integer.py
cs/maths/conversions/si_units.py
cs/maths/conversions/temperature.py
cs/structures/__init__.py
cs/structures/bloom_filter.py
cs/structures/disjoint_set.py
cs/structures/graph.py
cs/structures/lru_cache.py
cs/structures/queue.py
cs/structures/stack.py
cs/structures/suffix_array.py
cs/structures/trie.py
cs/structures/ado/__init__.py
cs/structures/ado/ado_finite_metric.py
cs/structures/ado/ado_graph.py
cs/structures/hash_table/__init__.py
cs/structures/hash_table/cuckoo.py
cs/structures/hash_table/hash_table.py
csworkshop-0.0.3.dist-info/LICENSE
csworkshop-0.0.3.dist-info/METADATA
csworkshop-0.0.3.dist-info/WHEEL
csworkshop-0.0.3.dist-info/top_level.txt
csworkshop-0.0.3.dist-info/RECORD
