Metadata-Version: 2.1
Name: csworkshop
Version: 0.0.3
Summary: CS Design Studio
Home-page: https://github.com/tyleryep/workshop
Author: Tyler Yep
Author-email: tyep@cs.stanford.edu
License: MIT
Classifier: License :: OSI Approved :: MIT License
Classifier: Operating System :: OS Independent
Classifier: Programming Language :: Python :: 3
Classifier: Programming Language :: Python :: 3 :: Only
Classifier: Programming Language :: Python :: 3.10
Classifier: Programming Language :: Python :: 3.11
Requires-Python: >=3.10
License-File: LICENSE
Requires-Dist: bitarray
Requires-Dist: prettyprinter
Requires-Dist: tqdm
